{"jenkins_event_timestamp":"1695670942420","jenkins_event_uuid":"4d9eac27-db27-4a1f-a590-3b4fda7fc0f6","jenkins_object_url":"job/nexoqa_training_playwright/job/main/","jenkins_object_name":"nexoqa_training_playwright/main","blueocean_job_pipeline_name":"nexoqa_training_playwright","jenkins_org":"jenkins","job_run_queueId":"7","blueocean_job_rest_url":"/blue/rest/organizations/jenkins/pipelines/nexoqa_training_playwright/pipelines/main/","jenkins_event":"job_run_queue_task_complete","jenkins_channel":"job","jenkins_object_type":"org.jenkinsci.plugins.workflow.job.WorkflowJob","job_name":"nexoqa_training_playwright/main","blueocean_job_branch_name":"main","jenkins_instance_url":"http://localhost:9090/"}